ovs/__init__.py
ovs/daemon.py
ovs/dirs.py
ovs/dns_resolve.py
ovs/fatal_signal.py
ovs/fcntl_win.py
ovs/json.py
ovs/jsonrpc.py
ovs/ovsuuid.py
ovs/poller.py
ovs/process.py
ovs/reconnect.py
ovs/socket_util.py
ovs/stream.py
ovs/timeval.py
ovs/util.py
ovs/version.py
ovs/vlog.py
ovs/winutils.py
ovs/compat/__init__.py
ovs/compat/sortedcontainers/__init__.py
ovs/compat/sortedcontainers/sorteddict.py
ovs/compat/sortedcontainers/sortedlist.py
ovs/compat/sortedcontainers/sortedset.py
ovs/db/__init__.py
ovs/db/custom_index.py
ovs/db/data.py
ovs/db/error.py
ovs/db/idl.py
ovs/db/parser.py
ovs/db/schema.py
ovs/db/types.py
ovs/flow/__init__.py
ovs/flow/decoders.py
ovs/flow/filter.py
ovs/flow/flow.py
ovs/flow/kv.py
ovs/flow/list.py
ovs/flow/odp.py
ovs/flow/ofp.py
ovs/flow/ofp_act.py
ovs/flow/ofp_fields.py
ovs/unixctl/__init__.py
ovs/unixctl/client.py
ovs/unixctl/server.py
nobidev_ovs-3.3.1.post2.dist-info/METADATA
nobidev_ovs-3.3.1.post2.dist-info/WHEEL
nobidev_ovs-3.3.1.post2.dist-info/top_level.txt
nobidev_ovs-3.3.1.post2.dist-info/RECORD
